zen_completions/__init__.py
zen_completions/cli.py
zen_completions/commands/__init__.py
zen_completions/commands/chat.py
zen_completions/commands/complete.py
zen_completions/commands/config.py
zen_completions/commands/prompt.py
zen_completions/models/__init__.py
zen_completions/models/config.py
zen_completions/models/enums.py
zen_completions/models/model_router.py
zen_completions/prompts/__init__.py
zen_completions/prompts/manager.py
zen_completions/zenapi/__init__.py
zen_completions/zenapi/completions.py
zen_completions-0.1.2.dist-info/METADATA
zen_completions-0.1.2.dist-info/WHEEL
zen_completions-0.1.2.dist-info/entry_points.txt
zen_completions-0.1.2.dist-info/RECORD
