Metadata-Version: 2.4
Name: zen-completions
Version: 0.1.2
Summary: A CLI tool for interacting with LLMs through a model router
Project-URL: Homepage, https://github.com/zenafide/zen-completions
Project-URL: Bug Tracker, https://github.com/zenafide/zen-completions/issues
Author-email: Zenafide Team <info@zenafide.com>
Classifier: License :: OSI Approved :: MIT License
Classifier: Operating System :: OS Independent
Classifier: Programming Language :: Python :: 3
Requires-Python: >=3.8
Requires-Dist: click>=8.1.3
Requires-Dist: cryptography>=41.0.0
Requires-Dist: langchain-community>=0.0.1
Requires-Dist: langchain-openai>=0.0.2
Requires-Dist: langchain>=0.0.267
Requires-Dist: openai>=1.1.0
Requires-Dist: pydantic>=2.0.0
Requires-Dist: python-dotenv>=1.0.0
Requires-Dist: rich>=13.4.2
